proxysocksrandom/__init__.py
proxysocksrandom-1.0.0.dist-info/METADATA
proxysocksrandom-1.0.0.dist-info/WHEEL
proxysocksrandom-1.0.0.dist-info/top_level.txt
proxysocksrandom-1.0.0.dist-info/RECORD
