Metadata-Version: 2.1
Name: proxysocksrandom
Version: 1.0.0
Summary: proxysocksrandom
Author: zelt-dev
Author-email: fgytre14@gmail.com
Classifier: Programming Language :: Python :: 3
Classifier: License :: OSI Approved :: MIT License
Classifier: Operating System :: OS Independent
Requires-Python: >=3.6
